mars_o_matic/__init__.py
mars_o_matic/skeleton.py
mars_o_matic-0.0.0.dist-info/AUTHORS.rst
mars_o_matic-0.0.0.dist-info/LICENSE.txt
mars_o_matic-0.0.0.dist-info/METADATA
mars_o_matic-0.0.0.dist-info/WHEEL
mars_o_matic-0.0.0.dist-info/top_level.txt
mars_o_matic-0.0.0.dist-info/RECORD
