Metadata-Version: 2.1
Name: mars-o-matic
Version: 0.0.0
Summary: Project to parse batch records and extract their datapoints
Home-page: https://github.com/pyscaffold/pyscaffold/
Author: Hugo Ehlinger
Author-email: hugo.ehlinger@capgemini.com
License: MIT
Project-URL: Documentation, https://pyscaffold.org/
Platform: any
Classifier: Development Status :: 4 - Beta
Classifier: Programming Language :: Python
Requires-Dist: importlib-metadata ; python_version < "3.8"
Provides-Extra: testing
Requires-Dist: setuptools ; extra == 'testing'
Requires-Dist: pytest ; extra == 'testing'
Requires-Dist: pytest-cov ; extra == 'testing'
